simple_genetic_package/__init__.py
simple_genetic_package/crossover.py
simple_genetic_package/mutation.py
simple_genetic_package/selection.py
simple_genetic_package-0.0.1.dist-info/METADATA
simple_genetic_package-0.0.1.dist-info/WHEEL
simple_genetic_package-0.0.1.dist-info/licenses/LICENSE
simple_genetic_package-0.0.1.dist-info/RECORD
